QOpenScienceFramework/__init__.py
QOpenScienceFramework/compat.py
QOpenScienceFramework/connection.py
QOpenScienceFramework/events.py
QOpenScienceFramework/loginwindow.py
QOpenScienceFramework/manager.py
QOpenScienceFramework/settings.json
QOpenScienceFramework/test-settings.json
QOpenScienceFramework/util.py
QOpenScienceFramework/img/cos-black.png
QOpenScienceFramework/img/cos-white2.png
QOpenScienceFramework/widgets/__init__.py
QOpenScienceFramework/widgets/loginwindow.py
QOpenScienceFramework/widgets/osfexplorer.py
QOpenScienceFramework/widgets/projecttree.py
QOpenScienceFramework/widgets/userbadge.py
python_qosf-1.3.1.dist-info/LICENSE
python_qosf-1.3.1.dist-info/METADATA
python_qosf-1.3.1.dist-info/WHEEL
python_qosf-1.3.1.dist-info/top_level.txt
python_qosf-1.3.1.dist-info/RECORD
