Metadata-Version: 2.1
Name: python-qosf
Version: 1.3.1
Summary: Qt widgets for the Open Science Framework
Home-page: https://github.com/dschreij/QOpenScienceFramework
Author: Daniel Schreij
Author-email: dschreij@gmail.com
License: UNKNOWN
Platform: UNKNOWN
Classifier: Intended Audience :: Science/Research
Classifier: Topic :: Scientific/Engineering
Classifier: Environment :: MacOS X
Classifier: Environment :: Win32 (MS Windows)
Classifier: Environment :: X11 Applications
Classifier: License :: OSI Approved :: Apache Software License
Classifier: Programming Language :: Python :: 2
Classifier: Programming Language :: Python :: 3
Requires-Dist: qtpy
Requires-Dist: arrow
Requires-Dist: humanize
Requires-Dist: python-fileinspector
Requires-Dist: requests-oauthlib (>=0.6)
Requires-Dist: qtawesome (>=0.5.7)
Requires-Dist: python-dotenv
